sartorial/__init__.py
sartorial/schema.py
sartorial/serialization.py
sartorial/types.py
sartorial-0.9.0.dist-info/METADATA
sartorial-0.9.0.dist-info/WHEEL
sartorial-0.9.0.dist-info/licenses/LICENSE
sartorial-0.9.0.dist-info/RECORD
